CHANGES.rst
CONTRIBUTORS.rst
LICENSE.rst
MANIFEST.in
README.rst
pyproject.toml
setup.py
docs/conf.py
docs/index.md
src/pas/__init__.py
src/pas.plugins.affinitic.egg-info/PKG-INFO
src/pas.plugins.affinitic.egg-info/SOURCES.txt
src/pas.plugins.affinitic.egg-info/dependency_links.txt
src/pas.plugins.affinitic.egg-info/entry_points.txt
src/pas.plugins.affinitic.egg-info/namespace_packages.txt
src/pas.plugins.affinitic.egg-info/not-zip-safe
src/pas.plugins.affinitic.egg-info/requires.txt
src/pas.plugins.affinitic.egg-info/top_level.txt
src/pas/plugins/__init__.py
src/pas/plugins/affinitic/__init__.py
src/pas/plugins/affinitic/configure.zcml
src/pas/plugins/affinitic/interfaces.py
src/pas/plugins/affinitic/permissions.zcml
src/pas/plugins/affinitic/plugin.py
src/pas/plugins/affinitic/setuphandlers.py
src/pas/plugins/affinitic/testing.py
src/pas/plugins/affinitic/utils.py
src/pas/plugins/affinitic/zmi.zpt
src/pas/plugins/affinitic/browser/__init__.py
src/pas/plugins/affinitic/browser/add_plugin.pt
src/pas/plugins/affinitic/browser/configure.zcml
src/pas/plugins/affinitic/browser/overrides/.gitkeep
src/pas/plugins/affinitic/browser/static/.gitkeep
src/pas/plugins/affinitic/locales/README.rst
src/pas/plugins/affinitic/locales/__init__.py
src/pas/plugins/affinitic/locales/pas.plugins.affinitic.pot
src/pas/plugins/affinitic/locales/update.py
src/pas/plugins/affinitic/locales/update.sh
src/pas/plugins/affinitic/locales/en/LC_MESSAGES/pas.plugins.affinitic.mo
src/pas/plugins/affinitic/locales/en/LC_MESSAGES/pas.plugins.affinitic.po
src/pas/plugins/affinitic/locales/fr/LC_MESSAGES/pas.plugins.affinitic.mo
src/pas/plugins/affinitic/locales/fr/LC_MESSAGES/pas.plugins.affinitic.po
src/pas/plugins/affinitic/profiles/default/browserlayer.xml
src/pas/plugins/affinitic/profiles/default/catalog.xml
src/pas/plugins/affinitic/profiles/default/metadata.xml
src/pas/plugins/affinitic/profiles/default/rolemap.xml
src/pas/plugins/affinitic/profiles/default/registry/main.xml
src/pas/plugins/affinitic/profiles/uninstall/browserlayer.xml
src/pas/plugins/affinitic/providers/__init__.py
src/pas/plugins/affinitic/providers/keycloak.py
src/pas/plugins/affinitic/providers/openidconnect.py
src/pas/plugins/affinitic/tests/__init__.py
src/pas/plugins/affinitic/tests/test_robot.py
src/pas/plugins/affinitic/tests/test_setup.py
src/pas/plugins/affinitic/tests/robot/test_example.robot