Metadata-Version: 2.1
Name: pas.plugins.affinitic
Version: 1.0.0a5
Summary: Collection of authentication tools and plugins
Home-page: https://github.com/affinitic/pas.plugins.affinitic
Author: Affinitic
Author-email: support@affinitic.be
License: GPL version 2
Project-URL: PyPI, https://pypi.python.org/pypi/pas.plugins.affinitic
Project-URL: Source, https://github.com/affinitic/pas.plugins.affinitic
Project-URL: Tracker, https://github.com/affinitic/pas.plugins.affinitic/issues
Keywords: Python Plone CMS
Classifier: Environment :: Web Environment
Classifier: Framework :: Plone
Classifier: Framework :: Plone :: Addon
Classifier: Framework :: Plone :: 4.3
Classifier: Framework :: Plone :: 6.0
Classifier: Programming Language :: Python
Classifier: Programming Language :: Python :: 2.7
Classifier: Programming Language :: Python :: 3.11
Classifier: Operating System :: OS Independent
Classifier: License :: OSI Approved :: GNU General Public License v2 (GPLv2)
Provides-Extra: test
License-File: LICENSE.rst
